kinielagpt/__init__.py
kinielagpt/__main__.py
kinielagpt/analyzer.py
kinielagpt/data_source.py
kinielagpt/detector.py
kinielagpt/predictor.py
kinielagpt/server.py
kinielagpt-1.0.3.dist-info/licenses/LICENSE
kinielagpt-1.0.3.dist-info/METADATA
kinielagpt-1.0.3.dist-info/WHEEL
kinielagpt-1.0.3.dist-info/entry_points.txt
kinielagpt-1.0.3.dist-info/top_level.txt
kinielagpt-1.0.3.dist-info/RECORD
