Metadata-Version: 2.4
Name: kinielagpt
Version: 1.0.3
Summary: MCP server for Spanish football quiniela predictions using LAE probabilities and match analysis
Author-email: Ricardo Moya <setmoya@gmail.com>
License-Expression: AGPL-3.0-or-later
Project-URL: Homepage, https://github.com/RicardoMoya/KinielaGPT
Project-URL: Documentation, https://ricardomoya.github.io/KinielaGPT/
Project-URL: Repository, https://github.com/RicardoMoya/KinielaGPT
Project-URL: Issues, https://github.com/RicardoMoya/KinielaGPT/issues
Project-URL: Discussions, https://github.com/RicardoMoya/KinielaGPT/discussions
Project-URL: LinkedIn, https://www.linkedin.com/in/phdricardomoya/
Keywords: mcp,quiniela,football,predictions,spain
Classifier: Development Status :: 4 - Beta
Classifier: Intended Audience :: Developers
Classifier: Programming Language :: Python :: 3
Classifier: Programming Language :: Python :: 3.10
Classifier: Programming Language :: Python :: 3.11
Classifier: Programming Language :: Python :: 3.12
Classifier: Programming Language :: Python :: 3.13
Classifier: Topic :: Games/Entertainment
Classifier: Topic :: Scientific/Engineering :: Artificial Intelligence
Requires-Python: >=3.10
License-File: LICENSE
Requires-Dist: mcp>=0.9.0
Requires-Dist: pandas>=2.0.0
Requires-Dist: requests>=2.31.0
Requires-Dist: xmltodict>=0.13.0
Provides-Extra: dev
Requires-Dist: pytest>=7.0.0; extra == "dev"
Requires-Dist: pytest-asyncio>=0.21.0; extra == "dev"
Requires-Dist: black>=23.0.0; extra == "dev"
Requires-Dist: mypy>=1.0.0; extra == "dev"
Requires-Dist: ruff>=0.1.0; extra == "dev"
Provides-Extra: docs
Requires-Dist: sphinx>=7.0.0; extra == "docs"
Requires-Dist: furo>=2025.0.0; extra == "docs"
Requires-Dist: sphinx-autodoc-typehints>=2.0.0; extra == "docs"
Requires-Dist: myst-parser>=3.0.0; extra == "docs"
Requires-Dist: sphinx-copybutton>=0.5.2; extra == "docs"
Dynamic: license-file
